Workbook
Name Slicer_AGE_GROUP: #N/A
Name Slicer_Category: #N/A
Name Slicer_Loyalyty: #N/A
Name Slicer_Region: #N/A

Sheet customer_imp
A1: Customer_ID | B1: Name | C1: Age | D1: Gender | E1: City | F1: State | G1: Country | H1: Loyalty_Level clean
A2: Cust1000 | B2: Sheena Bonilla | C2: 55 | D2: Male | E2: Donaldton | F2: North Carolina | G2: USA | H2: UnKno
A3: Cust1001 | B3: Eugene Nelson | C3: 26 | D3: Female | E3: Phillipsmouth | F3: North Dakota | G3: USA | H3: Platinum
A4: Cust1002 | B4: Dr. Benjamin Price | C4: 29 | D4: Female | E4: Kylebury | F4: Alabama | G4: USA | H4: Platinum
A5: Cust1003 | B5: Jeremy Harris | C5: 59 | D5: Female | E5: Thomastown | F5: Ohio | G5: USA | H5: Bronze
A6: Cust1004 | B6: Caroline Collins | C6: 64 | D6: Female | E6: Nicholasshire | F6: California | G6: USA | H6: Silver
A7: Cust1005 | B7: Christine Vaughn | C7: 24 | D7: Male | E7: East Amandamouth | F7: Oregon | G7: USA | H7: Bronze
A8: Cust1006 | B8: Amber Jackson | C8: 29 | D8: Female | E8: Deborahborough | F8: South Dakota | G8: USA | H8: Platinum
A9: Cust1007 | B9: Daniel Boyd | C9: 29 | D9: Female | E9: West Pamelafurt | F9: West Virginia | G9: USA | H9: Bronze
A10: Cust1008 | B10: Melissa Howard | C10: 53 | D10: Female | E10: Maynardton | F10: New Hampshire | G10: USA | H10: Gold
A11: Cust1009 | B11: Ms. Maria Leach | C11: 64 | D11: Male | E11: Melissashire | F11: Pennsylvania | G11: USA | H11: Platinum
A12: Cust1010 | B12: Dominic Page | C12: 53 | D12: Male | E12: Port Michaelburgh | F12: Pennsylvania | G12: USA | H12: Bronze
A13: Cust1011 | B13: Brian Lopez | C13: 28 | D13: Female | E13: East Krista | F13: New York | G13: USA | H13: Gold
... A501: Cust1499 | B501: Philip Pennington | C501: 27 | D501: Female | E501: East Valerieview | F501: Oregon | G501: USA | H501: Platinum

Sheet CUST
A1: Customer_ID | B1: Name | C1: Age | D1: Gender | E1: City | F1: State | G1: Country | H1: Loyalty_Level
A2: CUST1000 | B2: sheena bonilla | C2: 55 | D2: Male | E2: Donaldton | F2: North Carolina | G2: USA
A3: CUST1001 | B3: Eugene Nelson | C3: 26 | D3: Female | E3: Phillipsmouth | F3: North Dakota | G3: USA | H3: Platinum
A4: CUST1002 | B4: dr. Benjamin Price | C4: 29 | D4: Female | E4: Kylebury | F4: Alabama | G4: USA | H4: Platinum
A5: CUST1003 | B5: jeremy harris | C5: 59 | D5: Female | E5: Thomastown | F5: Ohio | G5: USA | H5: Bronze
A6: CUST1004 | B6: Caroline Collins | C6: 64 | D6: Female | E6: Nicholasshire | F6: California | G6: USA | H6: Silver
A7: CUST1005 | B7: Christine Vaughn | C7: 24 | D7: Male | E7: East Amandamouth | F7: Oregon | G7: USA | H7: Bronze
A8: CUST1006 | B8: Amber Jackson | C8: 29 | D8: Female | E8: Deborahborough | F8: South Dakota | G8: USA | H8: Platinum
A9: CUST1007 | B9: Daniel Boyd | C9: 29 | D9: Female | E9: West Pamelafurt | F9: West Virginia | G9: USA | H9: Bronze
A10: CUST1008 | B10: Melissa Howard | C10: 53 | D10: Female | E10: Maynardton | F10: New Hampshire | G10: USA | H10: Gold
A11: CUST1009 | B11: Ms. Maria Leach | C11: 64 | D11: Male | E11: Melissashire | F11: Pennsylvania | G11: USA | H11: Platinum
A12: CUST1010 | B12: Dominic Page | C12: 53 | D12: Male | E12: Port Michaelburgh | F12: Pennsylvania | G12: USA | H12: Bronze
A13: CUST1011 | B13: Brian Lopez | C13: 28 | D13: Female | E13: East Krista | F13: New York | G13: USA | H13: Gold
A14: CUST1012 | B14: Kenneth Lambert | C14: 55 | D14: Female | E14: North Kathryn | F14: Kansas | G14: USA | H14: Platinum
... A19: CUST1017 | B19: Adam Cruz | C19: 60 | D19: Female | E19: Brandonville | F19: Georgia | G19: USA | H19: Platinum
A20: CUST1018 | B20: Rhonda Moss | C20: 43 | D20: Male | E20: South William | F20: Kansas | G20: USA
A21: CUST1019 | B21: Michael Torres | C21: 46 | D21: Female | E21: Gonzalezfort | F21: New Jersey | G21: USA | H21: Platinum
A22: CUST1020 | B22: Bridget Allen | C22: 59 | D22: Male | E22: Lake Shaneburgh | F22: Delaware | G22: USA | H22: Silver
A23: CUST1021 | B23: Jeff Martinez | C23: 36 | D23: Female | E23: Smithburgh | F23: Oklahoma | G23: USA | H23: Gold
A24: CUST1022 | B24: paul fox | C24: 33 | D24: Female | E24: Michaelton | F24: Hawaii | G24: USA | H24: Silver
A25: CUST1023 | B25: Jonathan Steele | C25: 52 | D25: Female | E25: Molinabury | F25: Oregon | G25: USA | H25: Silver
A26: CUST1024 | B26: Heather Collins | C26: 40 | D26: Male | E26: Rogerschester | F26: Idaho | G26: USA | H26: Platinum
A27: CUST1025 | B27: Diana Taylor | C27: 59 | D27: Female | E27: Vasqueztown | F27: California | G27: USA | H27: Bronze
A28: CUST1026 | B28: Amber Carlson | C28: 18 | D28: Female | E28: East Michellemouth | F28: Missouri | G28: USA | H28: Gold
A29: CUST1027 | B29: Leslie Johnson | C29: 31 | D29: Male | E29: Mollyshire | F29: Utah | G29: USA
A30: CUST1028 | B30: Joshua Ryan | C30: 27 | D30: Female | E30: New David | F30: New Jersey | G30: USA | H30: Platinum
A31: CUST1029 | B31: David Arnold | C31: 54 | D31: Female | E31: East Jennifer | F31: California | G31: USA | H31: Silver
A32: CUST1030 | B32: Jessica Acevedo | C32: 64 | D32: Female | E32: Amybury | F32: Pennsylvania | G32: USA | H32: Bronze
A33: CUST1031 | B33: Sarah Vance | C33: 41 | D33: Male | E33: Johnsonville | F33: Oregon | G33: USA | H33: Silver
A34: CUST1032 | B34: Mike Jennings | C34: 48 | D34: Female | E34: Fostermouth | F34: Arizona | G34: USA | H34: Gold
A35: CUST1033 | B35: Robert Jones DDS | C35: 25 | D35: Male | E35: Tristanton | F35: Oklahoma | G35: USA | H35: Platinum
A36: CUST1034 | B36: Christopher Olson | C36: 27 | D36: Female | E36: West Richard | F36: Maryland | G36: USA | H36: Platinum
A37: CUST1035 | B37: Rachel Myers | C37: 52 | D37: Male | E37: Robertberg | F37: North Dakota | G37: USA | H37: Silver
A38: CUST1036 | B38: Thomas Phillips | C38: 20 | D38: Female | E38: Luisfurt | F38: Georgia | G38: USA | H38: Gold
A39: CUST1037 | B39: Christopher Carter | C39: 27 | D39: Female | E39: Brendastad | F39: South Dakota | G39: USA
A40: CUST1038 | B40: Deanna Simpson | C40: 35 | D40: Female | E40: Brownport | F40: North Dakota | G40: USA | H40: Bronze
A41: CUST1039 | B41: Tonya Reynolds | C41: 55 | D41: Female | E41: Darleneton | F41: Michigan | G41: USA | H41: Gold
A42: CUST1040 | B42: Eric Vega | C42: 50 | D42: Male | E42: Williamsonland | F42: Kansas | G42: USA | H42: Gold
A43: CUST1041 | B43: James Gibbs | C43: 21 | D43: Male | E43: Mooneyshire | F43: Alaska | G43: USA | H43: Platinum
A44: CUST1042 | B44: William Martin | C44: 19 | D44: Male | E44: Ryanburgh | F44: Connecticut | G44: USA | H44: Platinum
A45: CUST1043 | B45: Joseph Snow | C45: 45 | D45: Male | E45: South Michaelfort | F45: Vermont | G45: USA | H45: Gold
A46: CUST1044 | B46: Denise Williams | C46: 34 | D46: Male | E46: Christianstad | F46: Hawaii | G46: USA | H46: Bronze
A47: CUST1045 | B47: Jordan Jackson DDS | C47: 54 | D47: Male | E47: North Johnview | F47: Arizona | G47: USA | H47: Gold
A48: CUST1046 | B48: Michelle Garcia DDS | C48: 55 | D48: Female | E48: Perezbury | F48: Ohio | G48: USA | H48: Platinum
A49: CUST1047 | B49: Gina Knight | C49: 54 | D49: Female | E49: Lake Roberthaven | F49: Nevada | G49: USA | H49: Silver
A50: CUST1048 | B50: April Mullins | C50: 54 | D50: Male | E50: Dawsonbury | F50: North Carolina | G50: USA | H50: Platinum
A51: CUST1049 | B51: Timothy Weaver | C51: 45 | D51: Female | E51: New Amy | F51: Ohio | G51: USA | H51: Gold
... A501: C-1499 | B501: Philip Pennington | C501: 27 | D501: Female | E501: East Valerieview | F501: Oregon | G501: USA | H501: Platinum

Sheet prod_imp
A1: Product_ID | B1: Product_Name | C1: Category | D1: Sub_Category | E1: Brand | F1: Cost_clean | G1: Stock_clean
A2: Prod0 | B2: Brother Laser Printer | C2: Electronics | D2: Computer | E2: Hunt Inc | F2: 112 | G2: 416
A3: Prod1 | B3: Men'S Graphic T-Shirt | C3: Clothing | D3: Tops | E3: Terry-Moore | F3: 343 | G3: 181
A4: Prod2 | B4: Women'S Casual Hoodie | C4: Clothing | D4: Outerwear | E4: Sims Inc | F4: 317 | G4: 352
A5: Prod3 | B5: Men'S Running Jacket | C5: Clothing | D5: Outerwear | E5: Pineda Ltd | F5: 365 | G5: 452
A6: Prod4 | B6: Women'S Yoga Pants | C6: Clothing | D6: Bottoms | E6: Gonzales-Davis | F6: 306 | G6: 487
A7: Prod5 | B7: Men'S Leather Belt | C7: Clothing | D7: Accessories | E7: Baldwin, Garza And Gonzalez | F7: 261 | G7: 59
A8: Prod6 | B8: Herbal Face Moisturizer | C8: Beauty | D8: Skincare | E8: Davidson Plc | F8: 313 | G8: 350
A9: Prod7 | B9: Led Table Lamp | C9: Home | D9: Lighting | E9: Harrell Llc | F9: 219 | G9: 170
A10: Prod8 | B10: Wireless Bluetooth Earbuds | C10: Electronics | D10: Audio | E10: Perez-Johnston | F10: 439 | G10: 142
A11: Prod9 | B11: Adjustable Dumbbell Set | C11: Sports | D11: Fitness | E11: Hill Plc | F11: 496 | G11: 323
A12: Prod10 | B12: Ceramic Kitchen Bowl Set | C12: Home | D12: Kitchen | E12: Hamilton Group | F12: 299 | G12: 308
A13: Prod11 | B13: Hd Smart Tv Stick | C13: Electronics | D13: Accessories | E13: Gibson, Hobbs And Weaver | F13: 449 | G13: 275
... A101: Prod99 | B101: Stainless Steel Cookware Set | C101: Home | D101: Kitchen | E101: Campbell Ltd | F101: 201 | G101: 146

Sheet PRODS
A1: Product_ID | B1: Product_Name | C1: Category | D1: Sub_Category | E1: Brand | F1: Cost | G1: Stock
A2: PROD0 | B2: Brother Laser Printer | C2: Electronics | D2: Computer | E2: Hunt Inc | F2: 112.42 | G2: 416
A3: PROD1 | B3: Men's Graphic T-Shirt | C3: Clothing | D3: Tops | E3: Terry-Moore | F3: 342.56 | G3: 181
A4: PROD2 | B4: Women's Casual Hoodie | C4: Clothing | D4: Outerwear | E4: Sims Inc | G4: 352
A5: P-3 | B5: Men's Running Jacket | C5: Clothing | D5: Outerwear | E5: Pineda Ltd | F5: 364.67 | G5: 452
A6: PROD4 | B6: Women's Yoga Pants | C6: Clothing | D6: Bottoms | E6: Gonzales-Davis | F6: 306.46 | G6: 487
A7: PROD5 | B7: Men's Leather Belt | C7: Clothing | D7: Accessories | E7: Baldwin, Garza and Gonzalez | F7: 261 | G7: 59
A8: PROD6 | B8: Herbal Face Moisturizer | C8: Beauty | D8: Skincare | E8: Davidson PLC | F8: 312.8 | G8: 350
A9: PROD7 | B9: LED Table Lamp | C9: Home | D9: Lighting | E9: Harrell LLC | F9: 218.86 | G9: 170
A10: PROD8 | B10: Wireless Bluetooth Earbuds | C10: Electronics | D10: Audio | E10: Perez-Johnston | F10: 439.07 | G10: 142
A11: PROD9 | B11: Adjustable Dumbbell Set | C11: Sports | D11: Fitness | E11: Hill PLC | F11: 495.72 | G11: 323
A12: PROD10 | B12: Ceramic Kitchen Bowl Set | C12: Home | D12: Kitchen | E12: Hamilton Group | F12: 298.86 | G12: 308
A13: PROD11 | B13: HD Smart TV Stick | C13: Electronics | D13: Accessories | E13: Gibson, Hobbs and Weaver | F13: 449.4
A14: PROD12 | B14: Hair Strengthening Shampoo | C14: Beauty | D14: Haircare | E14: Rice LLC | F14: 115.82 | G14: 460
A15: PROD13 | B15: USB-C Fast Charger | C15: Electronics | D15: Accessories | E15: Dawson-Perkins | F15: 242.23 | G15: 453
A16: PROD14 | B16: Decorative Wall Mirror | C16: Home | D16: Decor | E16: Luna, Anderson and Bowman | F16: 48.01 | G16: 439
A17: PROD15 | B17: 4K Home Projector | C17: Electronics | D17: Appliances | E17: Thomas LLC | F17: 465.34 | G17: 301
A18: P-16 | B18: Beard Grooming Kit | C18: Beauty | D18: Grooming | E18: Erickson-Green | F18: 337.42 | G18: 256
A19: PROD17 | B19: Soccer Training Cone Set | C19: Sports | D19: Accessories | E19: Ford, Murphy and Wilson | F19: 144.53 | G19: 367
A20: PROD18 | B20: Women's Denim Jeans | C20: Clothing | D20: Bottoms | E20: Guerra-Hendrix | G20: 343
A21: PROD19 | B21: Knee Support Brace | C21: Sports | D21: Equipment | E21: May-Reese | F21: 21.34 | G21: 65
A22: PROD20 | B22: Outdoor Sports Water Bottle | C22: Sports | D22: Accessories | E22: Soto-Ellis | F22: 131.51
A23: PROD21 | B23: Multi-Purpose Storage Box | C23: Home | D23: Storage | E23: Gardner-Montes | F23: 123.46 | G23: 76
A24: PROD22 | B24: Carbon Fiber Tennis Racket | C24: Sports | D24: Equipment | E24: Flores, Pineda and Rodriguez | F24: 484.62 | G24: 432
A25: PROD23 | B25: Men's Formal Shirt | C25: Clothing | D25: Tops | E25: Moon, Mora and Santos | G25: 360
A26: PROD24 | B26: Foldable Camping Chair | C26: Sports | D26: Outdoor | E26: Cook Ltd | F26: 166.06 | G26: 340
A27: PROD25 | B27: Women's Scarf Set | C27: Clothing | D27: Accessories | E27: Brown and Sons | F27: 174.02 | G27: 268
A28: PROD26 | B28: Wireless Bluetooth Speaker | C28: Electronics | D28: Audio | E28: Reed-Schmidt | F28: 322.41 | G28: 213
A29: PROD27 | B29: Decorative Floor Vase | C29: Home | D29: Decor | E29: Khan, Jones and Paul | G29: 378
A30: PROD28 | B30: Sports Stopwatch Timer | C30: Sports | D30: Accessories | E30: Burns-Hansen | F30: 38.76 | G30: 137
A31: PROD29 | B31: Fabric Sofa Throw Blanket | C31: Home | D31: Decor | E31: Hoffman Group | F31: 218.48 | G31: 276
A32: PROD30 | B32: Stainless Steel Cutlery Set | C32: Home | D32: Kitchen | E32: Stevens, Fernandez and Martin | F32: 19.52 | G32: 57
A33: PROD31 | B33: Basketball | C33: Sports | D33: Team Sports | E33: Nolan-Snow | F33: 204.39 | G33: 281
A34: PROD32 | B34: Vitamin C Face Serum | C34: Beauty | D34: Skincare | E34: Griffin Ltd | F34: 283.83 | G34: 244
A35: PROD33 | B35: Modern Wall Clock | C35: Home | D35: Decor | E35: Weiss-Watson | F35: 179.77 | G35: 305
A36: PROD34 | B36: Gaming Mechanical Keyboard | C36: Electronics | D36: Computer | E36: Lucero LLC | F36: 419.28 | G36: 86
A37: PROD35 | B37: Bedroom Table Lamp | C37: Home | D37: Lighting | E37: Jones LLC | F37: 382.22 | G37: 329
A38: PROD36 | B38: Women's Summer Dress | C38: Clothing | D38: Tops | E38: Smith-Mills | F38: 223.43 | G38: 154
A39: PROD37 | B39: Men's Casual Sneakers | C39: Clothing | D39: Footwear | E39: Hogan-Lee | F39: 353.47 | G39: 214
A40: PROD38 | B40: Sports Water Hydration Pack | C40: Sports | D40: Outdoor | E40: Sims-Smith | F40: 135.61 | G40: 394
A41: PROD39 | B41: Portable Power Bank | C41: Electronics | D41: Mobile | E41: Cummings and Sons | F41: 326.06 | G41: 301
... A48: PROD46 | B48: Men's Winter Jacket | C48: Clothing | D48: Outerwear | E48: Kelly, Smith and Perez | F48: 167.34 | G48: 296
A49: PROD47 | B49: Makeup Brush Set | C49: Beauty | D49: Makeup | E49: Cook Inc | G49: 431
A50: PROD48 | B50: Car Dashboard Phone Holder | C50: Electronics | D50: Accessories | E50: Byrd, Stewart and Valdez | F50: 177.98 | G50: 103
A51: PROD49 | B51: Men's Roll-On Perfume | C51: Beauty | D51: Fragrance | E51: Sullivan and Sons | F51: 43.29 | G51: 267
A52: PROD50 | B52: Boxing Hand Wraps | C52: Sports | D52: Fitness | E52: Smith-King | F52: 190.29 | G52: 260
A53: PROD51 | B53: HDMI Cable – 2m | C53: Electronics | D53: Accessories | E53: Bautista, Green and Hale | F53: 88.49 | G53: 246
A54: PROD52 | B54: Rugby Ball | C54: Sports | D54: Team Sports | E54: Harris Inc | F54: 212.26 | G54: 82
A55: PROD53 | B55: Men's Track Pants | C55: Clothing | D55: Bottoms | E55: Hamilton, Woods and Walker | F55: 386.56 | G55: 125
A56: PROD54 | B56: Sports Stopwatch Pro | C56: Sports | D56: Accessories | E56: Thompson-French | F56: 434.84 | G56: 185
A57: PROD55 | B57: Ceramic Plant Pot | C57: Home | D57: Decor | E57: Hatfield, Baird and Torres | F57: 81.75
A58: PROD56 | B58: Premium Blanket Throw | C58: Home | D58: Decor | E58: Hernandez, Kennedy and Porter | F58: 461.47 | G58: 190
A59: PROD57 | B59: Foam Roller | C59: Sports | D59: Fitness | E59: Atkinson, Camacho and Oliver | F59: 30.62 | G59: 138
A60: PROD58 | B60: Womens Cotton Scarf | C60: Clothing | D60: Accessories | E60: Shepherd-Gould | F60: 113.83 | G60: 485
A61: PROD59 | B61: Men's Hair Styling Gel | C61: Beauty | D61: Haircare | E61: Cline-Mccarthy | F61: 17.31 | G61: 399
A62: PROD60 | B62: Luxury Perfume Spray | C62: Beauty | D62: Fragrance | E62: Gibson, Green and Lopez | F62: 482.75 | G62: 444
A63: PROD61 | B63: Tennis Ball 3-Pack | C63: Sports | D63: Equipment | E63: Lopez LLC | F63: 103.45 | G63: 465
A64: PROD62 | B64: Laptop Cooling Pad | C64: Electronics | D64: Computer | E64: Murray, Gould and Ware | F64: 86.42 | G64: 222
A65: PROD63 | B65: Organic Sunscreen Lotion | C65: Beauty | D65: Skincare | E65: Anderson-Riley | F65: 266.86 | G65: 458
A66: PROD64 | B66: Matte Lipstick Set | C66: Beauty | D66: Makeup | E66: Zhang Inc | F66: 299.11 | G66: 118
A67: PROD65 | B67: Adjustable Dumbbells 20kg | C67: Sports | D67: Fitness | E67: Montgomery, Benton and Miller | F67: 240.63 | G67: 423
A68: PROD66 | B68: Women's Hair Dryer Brush | C68: Beauty | D68: Haircare | E68: Torres, Spencer and Potter | F68: 340.39 | G68: 177
A69: PROD67 | B69: Smart LED Light Strip | C69: Electronics | D69: Accessories | E69: Flores-Davis | F69: 349.17 | G69: 476
... A84: PROD82 | B84: Fitness Resistance Bands | C84: Sports | D84: Fitness | E84: Reese-Watson | F84: 152.92 | G84: 281
A85: PROD83 | B85: Hydrating Face Cleanser | C85: Beauty | D85: Skincare | E85: Butler Group | G85: 159
A86: PROD84 | B86: Wooden Bookshelf | C86: Home | D86: Furniture | E86: Collins-Stephenson | F86: 388.46 | G86: 208
A87: PROD85 | B87: Women's Beanie Hat | C87: Clothing | D87: Accessories | E87: Richardson-Carrillo | F87: 119.57 | G87: 210
A88: PROD86 | B88: Kitchen Cutting Board | C88: Home | D88: Kitchen | E88: Taylor, Dodson and Johnston | F88: 176.07 | G88: 82
A89: PROD87 | B89: LED Bedside Lamp | C89: Home | D89: Lighting | E89: Aguilar, Horton and Lewis | F89: 371.38 | G89: 220
A90: PROD88 | B90: Sports Wrist Sweatbands | C90: Sports | D90: Accessories | E90: Olsen-Daniels | F90: 131.24 | G90: 232
A91: PROD89 | B91: Face Foundation Kit | C91: Beauty | D91: Makeup | E91: Taylor-Elliott | F91: 183.04 | G91: 457
A92: PROD90 | B92: Gaming Mouse Pad XL | C92: Electronics | D92: Accessories | E92: Sharp, Taylor and Rodriguez | F92: 340.14 | G92: 361
A93: PROD91 | B93: Women's High Heels | C93: Clothing | D93: Footwear | E93: Smith-Charles | F93: 438.25 | G93: 496
A94: PROD92 | B94: Microwave Oven | C94: Home | D94: Appliances | E94: Green, Powell and Palmer | F94: 447.43 | G94: 191
A95: PROD93 | B95: USB-C Laptop Charger | C95: Electronics | D95: Computer | E95: Martin LLC | F95: 377.52 | G95: 485
A96: PROD94 | B96: Vitamin E Body Lotion | C96: Beauty | D96: Skincare | E96: Hoffman-Williams | F96: 358.47 | G96: 213
A97: PROD95 | B97: Sports Stopwatch Basic | C97: Sports | D97: Accessories | E97: Wilson Group | F97: 60.65 | G97: 75
... A101: PROD99 | B101: Stainless Steel Cookware Set | C101: Home | D101: Kitchen | E101: Campbell Ltd | F101: 201.41 | G101: 146

Sheet stores_imp
A1: Store_ID | B1: Store_Name | C1: Region | D1: City | E1: Store_Type
A2: Store0 | B2: Rivera-Warner | C2: EAST | D2: Washingtonfurt | E2: Flagship
A3: Store1 | B3: Martinez, Adkins And Johnson | C3: NORTH | D3: Danielmouth | E3: Flagship
A4: Store2 | B4: Black-Horn | C4: SOUTH | D4: North Nancyview | E4: Outlet
A5: Store3 | B5: Johnson-Wright | C5: NORTH | D5: Hoodberg | E5: Outlet
A6: Store4 | B6: Alexander Group | C6: SOUTH | D6: Port Sharon | E6: Online
A7: Store5 | B7: Gray Ltd | C7: NORTH | D7: New Michaelchester | E7: Outlet
A8: Store6 | B8: Benson-Elliott | C8: EAST | D8: Port Josephberg | E8: Online
A9: Store7 | B9: Martinez-Mullins | C9: SOUTH | D9: Williamsfurt | E9: Online
A10: Store8 | B10: Bean, Jones And Park | C10: WEST | D10: Thompsonborough | E10: Online
A11: Store9 | B11: Moore, Padilla And Butler | C11: SOUTH | D11: East Johnstad | E11: Flagship
A12: Store10 | B12: Hill, Wagner And Ballard | C12: EAST | D12: East Davidville | E12: Online
... A21: Store19 | B21: Mann-Austin | C21: EAST | D21: Vasquezborough | E21: Online

Sheet STO
A1: Store_ID | B1: Store_Name | C1: Region | D1: City | E1: Store_Type
A2: STORE0 | B2: Rivera-Warner | C2: East | D2: Washingtonfurt | E2: Flagship
A3: STORE1 | B3: Martinez, Adkins and Johnson | C3: North | D3: Danielmouth | E3: Flagship
A4: STORE2 | B4: Black-Horn | C4: South | D4: North Nancyview | E4: Outlet
A5: STORE3 | B5: Johnson-Wright | C5: North | D5: Hoodberg | E5: Outlet
A6: STORE4 | B6: Alexander Group | C6: South | D6: Port Sharon | E6: Online
A7: STORE5 | B7: Gray Ltd | C7: North | D7: New Michaelchester | E7: Outlet
A8: STORE6 | B8: Benson-Elliott | C8: East | D8: Port Josephberg | E8: Online
A9: STORE7 | B9: Martinez-Mullins | C9: South | D9: Williamsfurt | E9: Online
A10: STORE8 | B10: Bean, Jones and Park | C10: West | D10: Thompsonborough | E10: Online
A11: STORE9 | B11: Moore, Padilla and Butler | C11: South | D11: East Johnstad | E11: Flagship
A12: STORE10 | B12: Hill, Wagner and Ballard | C12: East | D12: East Davidville | E12: Online
... A21: STORE19 | B21: Mann-Austin | C21: East | D21: Vasquezborough | E21: Online

Sheet Descriptive Statistics
A1: Total_Amount2 | C1: Quantity_imp | E1: Unit_Price2
A3: Mean | B3: 1087.6704 | C3: Mean | D3: 2.4812406 | E3: Mean | F3: 514.1971
A4: Standard Error | B4: 18.320224 | C4: Standard Error | D4: 0.024853327 | E4: Standard Error | F4: 6.3069449
A5: Median | B5: 871.40815 | C5: Median | D5: 2 | E5: Median | F5: 523
A6: Mode | B6: 1108.3151 | C6: Mode | D6: 2 | E6: Mode | F6: 846
A7: Standard Deviation | B7: 819.30534 | C7: Standard Deviation | D7: 1.1111967 | E7: Standard Deviation | F7: 281.98463
A8: Sample Variance | B8: 671261.24 | C8: Sample Variance | D8: 1.234758 | E8: Sample Variance | F8: 79515.33
A9: Kurtosis | B9: 0.047739484 | C9: Kurtosis | D9: -1.3435375 | E9: Kurtosis | F9: -1.1890448
A10: Skewness | B10: 0.87896511 | C10: Skewness | D10: 0.023179093 | E10: Skewness | F10: -0.037255334
A11: Range | B11: 3889.7838 | C11: Range | D11: 3 | E11: Range | F11: 980
A12: Minimum | B12: 18.459 | C12: Minimum | D12: 1 | E12: Minimum | F12: 20
A13: Maximum | B13: 3908.2428 | C13: Maximum | D13: 4 | E13: Maximum | F13: 1000
A14: Sum | B14: 2175340.7 | C14: Sum | D14: 4960 | E14: Sum | F14: 1027880
A15: Count | B15: 2000 | C15: Count | D15: 1999 | E15: Count | F15: 1999
B16: 1 | D16: 3 | F16: 5

Sheet Detail1
A1: Details for Average of Cost - Category: Clothing
A3: Sales_ID | B3: Order_Date | C3: Customer_ID | D3: Name | E3: Age | F3: Gender | G3: City | H3: State | I3: Country | J3: Loyalty _level | K3: Product_ID | L3: product_name | M3: Category | N3: Sub_Catagory | O3: Brand | P3: Cost | Q3: Stock | R3: Store_ID | S3: Payment_Type | T3: Total_Amount2 | U3: Quantity_imp | V3: Unit_Price2 | W3: Discount-im | X3: Region | Y3: Store_name | Z3: City2 | AA3: Store_Type | AB3: AGE GROUP
A4: Sale1981 | B4: 45648 | C4: Cust1264 | D4: Matthew Payne | E4: 25 | F4: Male | G4: Grahamfurt | H4: Wyoming | I4: USA | J4: Gold | K4: Prod36 | L4: Women'S Summer Dress | M4: Clothing | N4: Tops | O4: Smith-Mills | P4: 223 | Q4: 154 | R4: Store7 | S4: Credit Card | T4: 320.892 | U4: 1 | V4: 378 | W4: 0.01 | X4: SOUTH | Y4: Mann-Austin | Z4: Williamsfurt | AA4: Online | AB4: Adults
A5: Sale1979 | B5: 45666 | C5: Cust1309 | D5: Stacy Collins | E5: 41 | F5: Female | G5: Randychester | H5: California | I5: USA | J5: Bronze | K5: Prod46 | L5: Men'S Winter Jacket | M5: Clothing | N5: Outerwear | O5: Kelly, Smith And Perez | P5: 167 | Q5: 296 | R5: Store13 | S5: Paypal | T5: 1106.3094 | U5: 2 | V5: 636 | W5: 0.14 | X5: EAST | Y5: Gardner, Humphrey And Contreras | Z5: Johnsonville | AA5: Flagship | AB5: Elders
A6: Sale1975 | B6: 45390 | C6: Cust1300 | D6: Matthew Avery | E6: 29 | F6: Male | G6: Lake Melissashire | H6: Oregon | I6: USA | J6: Silver | K6: Prod5 | L6: Men'S Leather Belt | M6: Clothing | N6: Accessories | O6: Baldwin, Garza And Gonzalez | P6: 261 | Q6: 59 | R6: Store4 | S6: Cod | T6: 346.484 | U6: 2 | V6: 228 | W6: 0.25 | X6: SOUTH | Y6: Mann-Austin | Z6: Port Sharon | AA6: Online | AB6: Adults
A7: Sale1974 | B7: 45886 | C7: Cust1135 | D7: Matthew Hanna | E7: 33 | F7: Female | G7: Gonzalezbury | H7: Michigan | I7: USA | J7: Platinum | K7: Prod53 | L7: Men'S Track Pants | M7: Clothing | N7: Bottoms | O7: Hamilton, Woods And Walker | P7: 387 | Q7: 125 | R7: Store7 | S7: Cod | T7: 1264.335 | U7: 2 | V7: 843 | W7: 0.05 | X7: SOUTH | Y7: Mann-Austin | Z7: Williamsfurt | AA7: Online | AB7: Elders
A8: Sale1957 | B8: 45806 | C8: Cust1456 | D8: Julie Powell | E8: 59 | F8: Female | G8: South Barbara | H8: Arkansas | I8: USA | J8: Gold | K8: Prod37 | L8: Men'S Casual Sneakers | M8: Clothing | N8: Footwear | O8: Hogan-Lee | P8: 353 | Q8: 214 | R8: Store9 | S8: Credit Card | T8: 1882.1952 | U8: 3 | V8: 765 | W8: 0.02 | X8: SOUTH | Y8: Mann-Austin | Z8: East Johnstad | AA8: Flagship | AB8: Elders
A9: Sale1939 | B9: 45382 | C9: Cust1156 | D9: Maria Sanchez | E9: 46 | F9: Male | G9: East Peterbury | H9: North Dakota | I9: USA | J9: Bronze | K9: Prod96 | L9: Women'S Formal Blazer | M9: Clothing | N9: Outerwear | O9: Phillips And Sons | P9: 358 | Q9: 143 | R9: Store13 | S9: Paypal | T9: 1070.762 | U9: 2 | V9: 630 | W9: 0.15 | X9: EAST | Y9: Gardner, Humphrey And Contreras | Z9: Johnsonville | AA9: Flagship | AB9: Elders
A10: Sale1929 | B10: 45466 | C10: Cust1310 | D10: Kara Dodson | E10: 20 | F10: Male | G10: Joelside | H10: Vermont | I10: USA | J10: Silver | K10: Prod5 | L10: Men'S Leather Belt | M10: Clothing | N10: Accessories | O10: Baldwin, Garza And Gonzalez | P10: 261 | Q10: 59 | R10: Store5 | S10: Paypal | T10: 626.3712 | U10: 2 | V10: 344 | W10: 0.14 | X10: NORTH | Y10: Mann-Austin | Z10: New Michaelchester | AA10: Outlet | AB10: Adults
A11: Sale1922 | B11: 45276 | C11: Cust1247 | D11: Douglas Rhodes | E11: 32 | F11: Male | G11: Mikehaven | H11: New Hampshire | I11: USA | J11: Platinum | K11: Prod46 | L11: Men'S Winter Jacket | M11: Clothing | N11: Outerwear | O11: Kelly, Smith And Perez | P11: 167 | Q11: 296 | R11: Store17 | S11: Paypal | T11: 1662.5312 | U11: 4 | V11: 569 | W11: 0.3 | X11: NORTH | Y11: Holloway Ltd | Z11: Bensonhaven | AA11: Flagship | AB11: Elders
A12: Sale1905 | B12: 45760 | C12: Cust1176 | D12: John Bradford | E12: 48 | F12: Male | G12: Anabury | H12: Vermont | I12: USA | J12: Silver | K12: Prod75 | L12: Women'S Ankle Boots | M12: Clothing | N12: Footwear | O12: Poole Plc | P12: 158 | Q12: 82 | R12: Store12 | S12: Cod | T12: 793.3869 | U12: 1 | V12: 979 | W12: 0.08 | X12: NORTH | Y12: Thomas, Bridges And Harris | Z12: Sabrinatown | AA12: Online | AB12: Elders
A13: Sale1903 | B13: 45644 | C13: Cust1167 | D13: Antonio Wade | E13: 36 | F13: Female | G13: New Jasonmouth | H13: Tennessee | I13: USA | J13: Gold | K13: Prod3 | L13: Men'S Running Jacket | M13: Clothing | N13: Outerwear | O13: Pineda Ltd | P13: 365 | Q13: 452 | R13: Store0 | S13: Cod | T13: 1356.885 | U13: 3 | V13: 476 | W13: 0.12 | X13: EAST | Y13: Rivera-Warner | Z13: Washingtonfurt | AA13: Flagship | AB13: Elders
A14: Sale1902 | B14: 45691 | C14: Cust1455 | D14: Tyler Weber | E14: 54 | F14: Male | G14: East Yvette | H14: Illinois | I14: USA | J14: Gold | K14: Prod3 | L14: Men'S Running Jacket | M14: Clothing | N14: Outerwear | O14: Pineda Ltd | P14: 365 | Q14: 452 | R14: Store1 | S14: Credit Card | T14: 1046.5488 | U14: 2 | V14: 595 | W14: 0.27 | X14: NORTH | Y14: Martinez, Adkins And Johnson | Z14: Danielmouth | AA14: Flagship | AB14: Elders
A15: Sale1901 | B15: 45250 | C15: Cust1431 | D15: John Smith | E15: 27 | F15: Male | G15: South Andrewport | H15: California | I15: USA | J15: Platinum | K15: Prod25 | L15: Women'S Scarf Set | M15: Clothing | N15: Accessories | O15: Brown And Sons | P15: 174 | Q15: 268 | R15: Store8 | S15: Cod | T15: 38.0038 | U15: 1 | V15: 52 | W15: 0.12 | X15: WEST | Y15: Mann-Austin | Z15: Thompsonborough | AA15: Online | AB15: Adults
... A337: Sale335 | B337: 45309 | C337: Cust1458 | D337: Kelly Garrett | E337: 62 | F337: Female | G337: Port Taylorberg | H337: Pennsylvania | I337: USA | J337: Silver | K337: Prod2 | L337: Women'S Casual Hoodie | M337: Clothing | N337: Outerwear | O337: Sims Inc | P337: 317 | Q337: 352 | R337: Store14 | S337: Paypal | T337: 2799.072 | U337: 4 | V337: 972 | W337: 0.15 | X337: SOUTH | Y337: Mcdonald Inc | Z337: Christopherland | AA337: Outlet | AB337: Elders

Sheet Pivot Tables
B2: Average Sales Performance by category
A3: Row Labels | B3: Average of Cost | C3: Count of Brand
A4: Beauty | B4: 256.04605 | C4: 304
A5: Clothing | B5: 274.82635 | C5: 334
A6: Electronics | B6: 322.39427 | C6: 454
A7: Home | B7: 242.48537 | C7: 410
A8: Sports | B8: 209.00201 | C8: 498
S20: Average of Loyality level
S22: Average of Total_Amount2 | T22: Column Labels
S23: Row Labels | T23: Bronze | U23: Gold | V23: Platinum | W23: Silver | X23: UnKno | Y23: Grand Total
S24: EAST | T24: 961.34248 | U24: 1031.4149 | V24: 1142.1319 | W24: 1083.6996 | X24: 785.55466 | Y24: 1054.3523
S25: NORTH | T25: 1095.5326 | U25: 1153.6267 | V25: 1009.6754 | W25: 1105.4921 | X25: 1497.0836 | Y25: 1086.2137
A26: Gender wise overall sales by brand and catagory | S26: SOUTH | T26: 1146.6357 | U26: 1126.7757 | V26: 1029.0556 | W26: 1071.9303 | X26: 1578.6315 | Y26: 1093.31
A27: Sum of Total_Amount2 | B27: Column Labels | S27: WEST | T27: 1150.1837 | U27: 1085.4401 | V27: 1249.0805 | W27: 1131.9637 | X27: 959.6025 | Y27: 1161.7013
A28: Row Labels | B28: Beauty | C28: Clothing | D28: Electronics | E28: Home | F28: Sports | G28: Grand Total | S28: Grand Total | T28: 1073.1486 | U28: 1102.9949 | V28: 1084.1489 | W28: 1092.1947 | X28: 1094.521 | Y28: 1087.6704
A29: Female | B29: 20991.296 | C29: 42215.234 | D29: 85051.481 | F29: 68512.637 | G29: 216770.65
A30: Male | B30: 31359.231 | C30: 14720.811 | D30: 69135.482 | E30: 34823.064 | F30: 15805.213 | G30: 165843.8
A36: Average Unit price by top 10 state level and category base.
A37: Row Labels | B37: Average of Unit_Price2
A38: Alabama | B38: 551.63043
A39: Florida | B39: 564.09615
A40: Idaho | B40: 603.81818
A41: Indiana | B41: 598.76923
A42: Maine | B42: 552.86111
A43: Mississippi | B43: 652.65217
A44: Nebraska | B44: 560.72727
A45: Rhode Island | B45: 587.10345
A46: Utah | B46: 566
A47: Virginia | B47: 580.10638
P74: Averege sales by region
P75: Row Labels | Q75: Average of Total_Amount2
P76: EAST | Q76: 1054.3523
P77: NORTH | Q77: 1086.2137
P78: SOUTH | Q78: 1093.31
P79: WEST | Q79: 1161.7013
B83: Average Sales Performance by Gender
B84: Average of Total_Amount2
A85: Female | B85: 1123.5805
A86: Male | B86: 1044.1333
B90: Average Sales Performance by age group category wise
A91: Average of Total_Amount2 | B91: Column Labels
A92: Row Labels | B92: Beauty | C92: Clothing | D92: Electronics | E92: Home | F92: Sports
A93: Adults | B93: 1154.8594 | C93: 983.9813 | D93: 1143.0825 | E93: 956.75749 | F93: 1115.1254
A94: Elders | B94: 1034.8473 | C94: 1201.5335 | D94: 1088.8412 | E94: 1069.3138 | F94: 1068.6282
A95: Teens | B95: 1127.5306 | C95: 859.1873 | D95: 1401.5456 | E95: 885.08775 | F95: 1436.2975
A106: Top 10 Product sales person region wise
A107: Average of Total_Amount2 | B107: Column Labels
A108: Row Labels | B108: EAST | C108: NORTH | D108: SOUTH | E108: WEST
A109: Antonio Leon | B109: 2066.4262 | D109: 3032.656
A110: Crystal Waters | E110: 2343.4616
A111: Daniel Austin | B111: 2764.8032
A112: Joshua Wilson | B112: 1870.5871 | D112: 2801.768
A113: Julie Farmer | C113: 2319.4512
A114: Katherine Cowan | B114: 2221.2697
A115: Michael Mcneil | C115: 3502.9688 | Q115: Average sales by store names
A116: Steven Smith | B116: 3745.8048
A117: Tommy Roberts | B117: 3178.2564 | Q117: Average of Total_Amount2 | R117: Column Labels
A118: William Jackson | C118: 570.1176 | D118: 3756.8876 | Q118: Row Labels | R118: Flagship | S118: Online | T118: Outlet
Q119: Aguirre-Keller | S119: 1057.3652
Q120: Frederick-Wright | R120: 1053.8202
Q121: Gardner, Humphrey And Contreras | R121: 1204.226
Q122: Guerrero-Schmitt | R122: 993.45766
Q123: Holloway Ltd | R123: 1114.0906
Q124: Mann-Austin | R124: 1146.9 | S124: 1107.1982 | T124: 1059.6031
Q125: Martinez, Adkins And Johnson | R125: 1075.1129 | S125: 1128.6005
Q126: Mcdonald Inc | T126: 1118.403
Q127: Shelton Plc | R127: 1049.2535
Q128: Thomas, Bridges And Harris | S128: 1168.2922
O182: Top 10 Average city wise sales Performance
O185: Sum of Total_Amount2 | P185: Column Labels
O186: Row Labels | P186: Bronze | Q186: Gold | R186: Platinum | S186: Silver | T186: UnKno | U186: Grand Total
O187: Bensonhaven | P187: 27013.506 | Q187: 29090.975 | R187: 40242.702 | S187: 26202.789 | U187: 122549.97
O188: East Davidville | P188: 38894.413 | Q188: 17286.014 | R188: 26566.833 | S188: 26726.993 | U188: 109474.25
O189: East Johnstad | P189: 27549.578 | Q189: 33325.779 | R189: 23466.785 | S189: 23519.265 | T189: 2240.992 | U189: 110102.4
O190: Hoodberg | P190: 38505.258 | Q190: 31704.011 | R190: 29173.487 | S190: 25629.073 | U190: 125011.83
O191: Johnsonville | P191: 19266.281 | Q191: 24274.652 | R191: 47507.614 | S191: 22428.663 | T191: 924.262 | U191: 114401.47
O192: New Jimmymouth | P192: 23634.247 | Q192: 21446.857 | R192: 40656.827 | S192: 24047.808 | T192: 1919.205 | U192: 111704.94
O193: Port Josephberg | P193: 27329.406 | Q193: 15043.841 | R193: 49639.794 | S193: 20665.203 | T193: 1855.553 | U193: 114533.8
O194: Port Sharon | P194: 13550.255 | Q194: 34340.067 | R194: 35454.769 | S194: 35469.024 | U194: 118814.12
O195: Sabrinatown | P195: 34145.317 | Q195: 34524.776 | R195: 25475.252 | S195: 22683.875 | U195: 116829.22
O196: Thompsonborough | P196: 39625.858 | Q196: 37166.907 | R196: 53024.21 | S196: 29154.487 | U196: 158971.46
O197: Grand Total | P197: 289514.12 | Q197: 278203.88 | R197: 371208.27 | S197: 256527.18 | T197: 6940.012 | U197: 1202393.5

Sheet sale_imp
A1: Sales_ID | B1: Order_Date | C1: Customer_ID | D1: Name | E1: Age | F1: Gender | G1: City | H1: State | I1: Country | J1: Product_ID | K1: product_name | L1: Category | M1: Sub_Catagory | N1: Brand | O1: Cost | P1: Stock | Q1: Store_ID | R1: Payment_Type | S1: Total_Amount2 | T1: Quantity_imp | U1: Unit_Price2 | V1: Discount-im | W1: Region | X1: Store_name | Y1: City2 | Z1: Store_Type | AA1: AGE GROUP | AB1: Loyalyty
A2: Sale0 | B2: 45480 | C2: Cust1409 | D2: =VLOOKUP(C2,customer_imp!$A$2:$H$502,2,FALSE) -> Sarah Smith | E2: =VLOOKUP(C2,customer_imp!$A$2:$H$502,3,FALSE) -> 55 | F2: =VLOOKUP(C2,customer_imp!$A$2:$H$502,4,FALSE) -> Male | G2: =VLOOKUP(C2,customer_imp!$A$2:$H$502,5,FALSE) -> Kathleenport | H2: =VLOOKUP(C2,customer_imp!$A$2:$H$502,6,FALSE) -> Wyoming | I2: =VLOOKUP(C2,customer_imp!$A$2:$H$502,7,FALSE) -> USA | J2: Prod97 | K2: =VLOOKUP($J2,prod_imp!$A$2:$I$102,2,FALSE) -> Cricket Bat | L2: =VLOOKUP(J2,prod_imp!$A$2:$I$102,3,FALSE) -> Sports | M2: =VLOOKUP(J2,prod_imp!$A$2:$I$102,4,FALSE) -> Team Sports | N2: =VLOOKUP(J2,prod_imp!$A$2:$I$102,5,FALSE) -> Khan Llc | O2: =VLOOKUP(J2,prod_imp!$A$2:$I$102,6,FALSE) -> 246 | P2: =VLOOKUP(J2,prod_imp!$A$2:$I$102,7,FALSE) -> 471 | Q2: Store3 | R2: Credit Card | S2: 198.4164 | T2: 1 | U2: 218 | V2: 0.06 | W2: =VLOOKUP(Q2,stores_imp!$A$2:$K$100,3,FALSE) -> NORTH | X2: =VLOOKUP(Q2,stores_imp!$A$2:$K$100,2,TRUE) -> Mann-Austin | Y2: =VLOOKUP(Q2,stores_imp!$A$2:$E$22,4,FALSE) -> Hoodberg | Z2: =VLOOKUP(Q2,stores_imp!$A$2:$K$22,5,FALSE) -> Outlet | AA2: =_xlfn.IFS(sale[[#All],[Age]]<19,"Teens",sale[[#All],[Age]]<30,"Adults",sale[[#All],[Age]]<70,"Elders") -> Elders | AB2: =VLOOKUP(C2,customer_imp!$A$2:$H$505,8,FALSE) -> Gold
A3: Sale1 | B3: 45285 | C3: Cust1467 | D3: =VLOOKUP(C3,customer_imp!$A$2:$H$502,2,FALSE) -> Michael Foley | E3: =VLOOKUP(C3,customer_imp!$A$2:$H$502,3,FALSE) -> 63 | F3: =VLOOKUP(C3,customer_imp!$A$2:$H$502,4,FALSE) -> Female | G3: =VLOOKUP(C3,customer_imp!$A$2:$H$502,5,FALSE) -> Oneillfurt | H3: =VLOOKUP(C3,customer_imp!$A$2:$H$502,6,FALSE) -> Vermont | I3: =VLOOKUP(C3,customer_imp!$A$2:$H$502,7,FALSE) -> USA | J3: Prod74 | K3: =VLOOKUP($J3,prod_imp!$A$2:$I$102,2,FALSE) -> Bluetooth Car Audio System | L3: =VLOOKUP(J3,prod_imp!$A$2:$I$102,3,FALSE) -> Electronics | M3: =VLOOKUP(J3,prod_imp!$A$2:$I$102,4,FALSE) -> Audio | N3: =VLOOKUP(J3,prod_imp!$A$2:$I$102,5,FALSE) -> Bruce-Bowen | O3: =VLOOKUP(J3,prod_imp!$A$2:$I$102,6,FALSE) -> 404 | P3: =VLOOKUP(J3,prod_imp!$A$2:$I$102,7,FALSE) -> 159 | Q3: Store17 | R3: Paypal | S3: 228.7893 | T3: 3 | U3: 104 | V3: 0.09 | W3: =VLOOKUP(Q3,stores_imp!$A$2:$K$100,3,FALSE) -> NORTH | X3: =VLOOKUP(Q3,stores_imp!$A$2:$K$100,2,TRUE) -> Holloway Ltd | Y3: =VLOOKUP(Q3,stores_imp!$A$2:$E$22,4,FALSE) -> Bensonhaven | Z3: =VLOOKUP(Q3,stores_imp!$A$2:$K$22,5,FALSE) -> Flagship | AA3: =_xlfn.IFS(sale[[#All],[Age]]<19,"Teens",sale[[#All],[Age]]<30,"Adults",sale[[#All],[Age]]<70,"Elders") -> Elders | AB3: =VLOOKUP(C3,customer_imp!$A$2:$H$505,8,FALSE) -> Gold
A4: Sale2 | B4: 45446 | C4: Cust1056 | D4: =VLOOKUP(C4,customer_imp!$A$2:$H$502,2,FALSE) -> Christopher Sutton | E4: =VLOOKUP(C4,customer_imp!$A$2:$H$502,3,FALSE) -> 49 | F4: =VLOOKUP(C4,customer_imp!$A$2:$H$502,4,FALSE) -> Female | G4: =VLOOKUP(C4,customer_imp!$A$2:$H$502,5,FALSE) -> Deborahberg | H4: =VLOOKUP(C4,customer_imp!$A$2:$H$502,6,FALSE) -> Pennsylvania | I4: =VLOOKUP(C4,customer_imp!$A$2:$H$502,7,FALSE) -> USA | J4: Prod49 | K4: =VLOOKUP($J4,prod_imp!$A$2:$I$102,2,FALSE) -> Men'S Roll-On Perfume | L4: =VLOOKUP(J4,prod_imp!$A$2:$I$102,3,FALSE) -> Beauty | M4: =VLOOKUP(J4,prod_imp!$A$2:$I$102,4,FALSE) -> Fragrance | N4: =VLOOKUP(J4,prod_imp!$A$2:$I$102,5,FALSE) -> Sullivan And Sons | O4: =VLOOKUP(J4,prod_imp!$A$2:$I$102,6,FALSE) -> 43 | P4: =VLOOKUP(J4,prod_imp!$A$2:$I$102,7,FALSE) -> 267 | Q4: Store8 | R4: Credit Card | S4: 2742.15 | T4: 4 | U4: 914 | V4: 0.27 | W4: =VLOOKUP(Q4,stores_imp!$A$2:$K$100,3,FALSE) -> WEST | X4: =VLOOKUP(Q4,stores_imp!$A$2:$K$100,2,TRUE) -> Mann-Austin | Y4: =VLOOKUP(Q4,stores_imp!$A$2:$E$22,4,FALSE) -> Thompsonborough | Z4: =VLOOKUP(Q4,stores_imp!$A$2:$K$22,5,FALSE) -> Online | AA4: =_xlfn.IFS(sale[[#All],[Age]]<19,"Teens",sale[[#All],[Age]]<30,"Adults",sale[[#All],[Age]]<70,"Elders") -> Elders | AB4: =VLOOKUP(C4,customer_imp!$A$2:$H$505,8,FALSE) -> Gold
A5: Sale3 | B5: 45259 | C5: Cust1346 | D5: =VLOOKUP(C5,customer_imp!$A$2:$H$502,2,FALSE) -> John Jordan | E5: =VLOOKUP(C5,customer_imp!$A$2:$H$502,3,FALSE) -> 58 | F5: =VLOOKUP(C5,customer_imp!$A$2:$H$502,4,FALSE) -> Female | G5: =VLOOKUP(C5,customer_imp!$A$2:$H$502,5,FALSE) -> Port Crystalberg | H5: =VLOOKUP(C5,customer_imp!$A$2:$H$502,6,FALSE) -> Tennessee | I5: =VLOOKUP(C5,customer_imp!$A$2:$H$502,7,FALSE) -> USA | J5: Prod76 | K5: =VLOOKUP($J5,prod_imp!$A$2:$I$102,2,FALSE) -> Wireless Mouse | L5: =VLOOKUP(J5,prod_imp!$A$2:$I$102,3,FALSE) -> Electronics | M5: =VLOOKUP(J5,prod_imp!$A$2:$I$102,4,FALSE) -> Computer | N5: =VLOOKUP(J5,prod_imp!$A$2:$I$102,5,FALSE) -> Larson Ltd | O5: =VLOOKUP(J5,prod_imp!$A$2:$I$102,6,FALSE) -> 393 | P5: =VLOOKUP(J5,prod_imp!$A$2:$I$102,7,FALSE) -> 320 | Q5: Store8 | R5: Cod | S5: 774.0684 | T5: 1 | U5: 922 | V5: 0.25 | W5: =VLOOKUP(Q5,stores_imp!$A$2:$K$100,3,FALSE) -> WEST | X5: =VLOOKUP(Q5,stores_imp!$A$2:$K$100,2,TRUE) -> Mann-Austin | Y5: =VLOOKUP(Q5,stores_imp!$A$2:$E$22,4,FALSE) -> Thompsonborough | Z5: =VLOOKUP(Q5,stores_imp!$A$2:$K$22,5,FALSE) -> Online | AA5: =_xlfn.IFS(sale[[#All],[Age]]<19,"Teens",sale[[#All],[Age]]<30,"Adults",sale[[#All],[Age]]<70,"Elders") -> Elders | AB5: =VLOOKUP(C5,customer_imp!$A$2:$H$505,8,FALSE) -> Platinum
A6: Sale4 | B6: 45297 | C6: Cust1493 | D6: =VLOOKUP(C6,customer_imp!$A$2:$H$502,2,FALSE) -> Amanda Powell | E6: =VLOOKUP(C6,customer_imp!$A$2:$H$502,3,FALSE) -> 28 | F6: =VLOOKUP(C6,customer_imp!$A$2:$H$502,4,FALSE) -> Male | G6: =VLOOKUP(C6,customer_imp!$A$2:$H$502,5,FALSE) -> South William | H6: =VLOOKUP(C6,customer_imp!$A$2:$H$502,6,FALSE) -> Alabama | I6: =VLOOKUP(C6,customer_imp!$A$2:$H$502,7,FALSE) -> USA | J6: Prod59 | K6: =VLOOKUP($J6,prod_imp!$A$2:$I$102,2,FALSE) -> Men'S Hair Styling Gel | L6: =VLOOKUP(J6,prod_imp!$A$2:$I$102,3,FALSE) -> Beauty | M6: =VLOOKUP(J6,prod_imp!$A$2:$I$102,4,FALSE) -> Haircare | N6: =VLOOKUP(J6,prod_imp!$A$2:$I$102,5,FALSE) -> Cline-Mccarthy | O6: =VLOOKUP(J6,prod_imp!$A$2:$I$102,6,FALSE) -> 17 | P6: =VLOOKUP(J6,prod_imp!$A$2:$I$102,7,FALSE) -> 399 | Q6: Store5 | R6: Credit Card | S6: 1833.438 | T6: 3 | U6: 745 | V6: 0.16 | W6: =VLOOKUP(Q6,stores_imp!$A$2:$K$100,3,FALSE) -> NORTH | X6: =VLOOKUP(Q6,stores_imp!$A$2:$K$100,2,TRUE) -> Mann-Austin | Y6: =VLOOKUP(Q6,stores_imp!$A$2:$E$22,4,FALSE) -> New Michaelchester | Z6: =VLOOKUP(Q6,stores_imp!$A$2:$K$22,5,FALSE) -> Outlet | AA6: =_xlfn.IFS(sale[[#All],[Age]]<19,"Teens",sale[[#All],[Age]]<30,"Adults",sale[[#All],[Age]]<70,"Elders") -> Adults | AB6: =VLOOKUP(C6,customer_imp!$A$2:$H$505,8,FALSE) -> Silver
A7: Sale5 | B7: 45499 | C7: Cust1116 | D7: =VLOOKUP(C7,customer_imp!$A$2:$H$502,2,FALSE) -> Anthony Phillips | E7: =VLOOKUP(C7,customer_imp!$A$2:$H$502,3,FALSE) -> 18 | F7: =VLOOKUP(C7,customer_imp!$A$2:$H$502,4,FALSE) -> Female | G7: =VLOOKUP(C7,customer_imp!$A$2:$H$502,5,FALSE) -> North Davidport | H7: =VLOOKUP(C7,customer_imp!$A$2:$H$502,6,FALSE) -> Rhode Island | I7: =VLOOKUP(C7,customer_imp!$A$2:$H$502,7,FALSE) -> USA | J7: Prod15 | K7: =VLOOKUP($J7,prod_imp!$A$2:$I$102,2,FALSE) -> 4K Home Projector | L7: =VLOOKUP(J7,prod_imp!$A$2:$I$102,3,FALSE) -> Electronics | M7: =VLOOKUP(J7,prod_imp!$A$2:$I$102,4,FALSE) -> Appliances | N7: =VLOOKUP(J7,prod_imp!$A$2:$I$102,5,FALSE) -> Thomas Llc | O7: =VLOOKUP(J7,prod_imp!$A$2:$I$102,6,FALSE) -> 465 | P7: =VLOOKUP(J7,prod_imp!$A$2:$I$102,7,FALSE) -> 301 | Q7: Store7 | R7: Cod | S7: 357.2343 | T7: 3 | U7: 147 | V7: 0.18 | W7: =VLOOKUP(Q7,stores_imp!$A$2:$K$100,3,FALSE) -> SOUTH | X7: =VLOOKUP(Q7,stores_imp!$A$2:$K$100,2,TRUE) -> Mann-Austin | Y7: =VLOOKUP(Q7,stores_imp!$A$2:$E$22,4,FALSE) -> Williamsfurt | Z7: =VLOOKUP(Q7,stores_imp!$A$2:$K$22,5,FALSE) -> Online | AA7: =_xlfn.IFS(sale[[#All],[Age]]<19,"Teens",sale[[#All],[Age]]<30,"Adults",sale[[#All],[Age]]<70,"Elders") -> Teens | AB7: =VLOOKUP(C7,customer_imp!$A$2:$H$505,8,FALSE) -> Platinum
A8: Sale6 | B8: 45850 | C8: Cust1016 | D8: =VLOOKUP(C8,customer_imp!$A$2:$H$502,2,FALSE) -> John Scott | E8: =VLOOKUP(C8,customer_imp!$A$2:$H$502,3,FALSE) -> 24 | F8: =VLOOKUP(C8,customer_imp!$A$2:$H$502,4,FALSE) -> Female | G8: =VLOOKUP(C8,customer_imp!$A$2:$H$502,5,FALSE) -> South Christopher | H8: =VLOOKUP(C8,customer_imp!$A$2:$H$502,6,FALSE) -> Pennsylvania | I8: =VLOOKUP(C8,customer_imp!$A$2:$H$502,7,FALSE) -> USA | J8: Prod56 | K8: =VLOOKUP($J8,prod_imp!$A$2:$I$102,2,FALSE) -> Premium Blanket Throw | L8: =VLOOKUP(J8,prod_imp!$A$2:$I$102,3,FALSE) -> Home | M8: =VLOOKUP(J8,prod_imp!$A$2:$I$102,4,FALSE) -> Decor | N8: =VLOOKUP(J8,prod_imp!$A$2:$I$102,5,FALSE) -> Hernandez, Kennedy And Porter | O8: =VLOOKUP(J8,prod_imp!$A$2:$I$102,6,FALSE) -> 461 | P8: =VLOOKUP(J8,prod_imp!$A$2:$I$102,7,FALSE) -> 190 | Q8: Store4 | R8: Paypal | S8: 1335.027 | T8: 2 | U8: 785 | V8: 0.19 | W8: =VLOOKUP(Q8,stores_imp!$A$2:$K$100,3,FALSE) -> SOUTH | X8: =VLOOKUP(Q8,stores_imp!$A$2:$K$100,2,TRUE) -> Mann-Austin | Y8: =VLOOKUP(Q8,stores_imp!$A$2:$E$22,4,FALSE) -> Port Sharon | Z8: =VLOOKUP(Q8,stores_imp!$A$2:$K$22,5,FALSE) -> Online | AA8: =_xlfn.IFS(sale[[#All],[Age]]<19,"Teens",sale[[#All],[Age]]<30,"Adults",sale[[#All],[Age]]<70,"Elders") -> Adults | AB8: =VLOOKUP(C8,customer_imp!$A$2:$H$505,8,FALSE) -> Bronze
A9: Sale7 | B9: 45248 | C9: Cust1152 | D9: =VLOOKUP(C9,customer_imp!$A$2:$H$502,2,FALSE) -> Patrick Roberts | E9: =VLOOKUP(C9,customer_imp!$A$2:$H$502,3,FALSE) -> 41 | F9: =VLOOKUP(C9,customer_imp!$A$2:$H$502,4,FALSE) -> Female | G9: =VLOOKUP(C9,customer_imp!$A$2:$H$502,5,FALSE) -> Jaredville | H9: =VLOOKUP(C9,customer_imp!$A$2:$H$502,6,FALSE) -> Missouri | I9: =VLOOKUP(C9,customer_imp!$A$2:$H$502,7,FALSE) -> USA | J9: Prod70 | K9: =VLOOKUP($J9,prod_imp!$A$2:$I$102,2,FALSE) -> Kitchen Storage Rack | L9: =VLOOKUP(J9,prod_imp!$A$2:$I$102,3,FALSE) -> Home | M9: =VLOOKUP(J9,prod_imp!$A$2:$I$102,4,FALSE) -> Storage | N9: =VLOOKUP(J9,prod_imp!$A$2:$I$102,5,FALSE) -> Duran Group | O9: =VLOOKUP(J9,prod_imp!$A$2:$I$102,6,FALSE) -> 138 | P9: =VLOOKUP(J9,prod_imp!$A$2:$I$102,7,FALSE) -> 89 | Q9: Store8 | R9: Paypal | S9: 1054.5612 | T9: 4 | U9: 342 | V9: 0.15 | W9: =VLOOKUP(Q9,stores_imp!$A$2:$K$100,3,FALSE) -> WEST | X9: =VLOOKUP(Q9,stores_imp!$A$2:$K$100,2,TRUE) -> Mann-Austin | Y9: =VLOOKUP(Q9,stores_imp!$A$2:$E$22,4,FALSE) -> Thompsonborough | Z9: =VLOOKUP(Q9,stores_imp!$A$2:$K$22,5,FALSE) -> Online | AA9: =_xlfn.IFS(sale[[#All],[Age]]<19,"Teens",sale[[#All],[Age]]<30,"Adults",sale[[#All],[Age]]<70,"Elders") -> Elders | AB9: =VLOOKUP(C9,customer_imp!$A$2:$H$505,8,FALSE) -> Platinum
A10: Sale8 | B10: 45781 | C10: Cust1187 | D10: =VLOOKUP(C10,customer_imp!$A$2:$H$502,2,FALSE) -> Dr. Suzanne Bullock | E10: =VLOOKUP(C10,customer_imp!$A$2:$H$502,3,FALSE) -> 60 | F10: =VLOOKUP(C10,customer_imp!$A$2:$H$502,4,FALSE) -> Female | G10: =VLOOKUP(C10,customer_imp!$A$2:$H$502,5,FALSE) -> Lake Blaketon | H10: =VLOOKUP(C10,customer_imp!$A$2:$H$502,6,FALSE) -> Alabama | I10: =VLOOKUP(C10,customer_imp!$A$2:$H$502,7,FALSE) -> USA | J10: Prod99 | K10: =VLOOKUP($J10,prod_imp!$A$2:$I$102,2,FALSE) -> Stainless Steel Cookware Set | L10: =VLOOKUP(J10,prod_imp!$A$2:$I$102,3,FALSE) -> Home | M10: =VLOOKUP(J10,prod_imp!$A$2:$I$102,4,FALSE) -> Kitchen | N10: =VLOOKUP(J10,prod_imp!$A$2:$I$102,5,FALSE) -> Campbell Ltd | O10: =VLOOKUP(J10,prod_imp!$A$2:$I$102,6,FALSE) -> 201 | P10: =VLOOKUP(J10,prod_imp!$A$2:$I$102,7,FALSE) -> 146 | Q10: Store5 | R10: Paypal | S10: 1250.6175 | T10: 3 | U10: 448 | V10: 0.23 | W10: =VLOOKUP(Q10,stores_imp!$A$2:$K$100,3,FALSE) -> NORTH | X10: =VLOOKUP(Q10,stores_imp!$A$2:$K$100,2,TRUE) -> Mann-Austin | Y10: =VLOOKUP(Q10,stores_imp!$A$2:$E$22,4,FALSE) -> New Michaelchester | Z10: =VLOOKUP(Q10,stores_imp!$A$2:$K$22,5,FALSE) -> Outlet | AA10: =_xlfn.IFS(sale[[#All],[Age]]<19,"Teens",sale[[#All],[Age]]<30,"Adults",sale[[#All],[Age]]<70,"Elders") -> Elders | AB10: =VLOOKUP(C10,customer_imp!$A$2:$H$505,8,FALSE) -> Platinum
A11: Sale9 | B11: 45869 | C11: Cust1464 | D11: =VLOOKUP(C11,customer_imp!$A$2:$H$502,2,FALSE) -> David Pierce | E11: =VLOOKUP(C11,customer_imp!$A$2:$H$502,3,FALSE) -> 45 | F11: =VLOOKUP(C11,customer_imp!$A$2:$H$502,4,FALSE) -> Female | G11: =VLOOKUP(C11,customer_imp!$A$2:$H$502,5,FALSE) -> Grayland | H11: =VLOOKUP(C11,customer_imp!$A$2:$H$502,6,FALSE) -> Washington | I11: =VLOOKUP(C11,customer_imp!$A$2:$H$502,7,FALSE) -> USA | J11: Prod33 | K11: =VLOOKUP($J11,prod_imp!$A$2:$I$102,2,FALSE) -> Modern Wall Clock | L11: =VLOOKUP(J11,prod_imp!$A$2:$I$102,3,FALSE) -> Home | M11: =VLOOKUP(J11,prod_imp!$A$2:$I$102,4,FALSE) -> Decor | N11: =VLOOKUP(J11,prod_imp!$A$2:$I$102,5,FALSE) -> Weiss-Watson | O11: =VLOOKUP(J11,prod_imp!$A$2:$I$102,6,FALSE) -> 180 | P11: =VLOOKUP(J11,prod_imp!$A$2:$I$102,7,FALSE) -> 305 | Q11: Store0 | R11: Paypal | S11: 1344.6818 | T11: 2 | U11: 873 | V11: 0.07 | W11: =VLOOKUP(Q11,stores_imp!$A$2:$K$100,3,FALSE) -> EAST | X11: =VLOOKUP(Q11,stores_imp!$A$2:$K$100,2,TRUE) -> Rivera-Warner | Y11: =VLOOKUP(Q11,stores_imp!$A$2:$E$22,4,FALSE) -> Washingtonfurt | Z11: =VLOOKUP(Q11,stores_imp!$A$2:$K$22,5,FALSE) -> Flagship | AA11: =_xlfn.IFS(sale[[#All],[Age]]<19,"Teens",sale[[#All],[Age]]<30,"Adults",sale[[#All],[Age]]<70,"Elders") -> Elders | AB11: =VLOOKUP(C11,customer_imp!$A$2:$H$505,8,FALSE) -> Platinum
A12: Sale10 | B12: 45335 | C12: Cust1065 | D12: =VLOOKUP(C12,customer_imp!$A$2:$H$502,2,FALSE) -> Michael Thomas | E12: =VLOOKUP(C12,customer_imp!$A$2:$H$502,3,FALSE) -> 21 | F12: =VLOOKUP(C12,customer_imp!$A$2:$H$502,4,FALSE) -> Female | G12: =VLOOKUP(C12,customer_imp!$A$2:$H$502,5,FALSE) -> Woodmouth | H12: =VLOOKUP(C12,customer_imp!$A$2:$H$502,6,FALSE) -> Nevada | I12: =VLOOKUP(C12,customer_imp!$A$2:$H$502,7,FALSE) -> USA | J12: Prod24 | K12: =VLOOKUP($J12,prod_imp!$A$2:$I$102,2,FALSE) -> Foldable Camping Chair | L12: =VLOOKUP(J12,prod_imp!$A$2:$I$102,3,FALSE) -> Sports | M12: =VLOOKUP(J12,prod_imp!$A$2:$I$102,4,FALSE) -> Outdoor | N12: =VLOOKUP(J12,prod_imp!$A$2:$I$102,5,FALSE) -> Cook Ltd | O12: =VLOOKUP(J12,prod_imp!$A$2:$I$102,6,FALSE) -> 166 | P12: =VLOOKUP(J12,prod_imp!$A$2:$I$102,7,FALSE) -> 340 | Q12: Store14 | R12: Credit Card | S12: 259.1259 | T12: 1 | U12: 279 | V12: 0.23 | W12: =VLOOKUP(Q12,stores_imp!$A$2:$K$100,3,FALSE) -> SOUTH | X12: =VLOOKUP(Q12,stores_imp!$A$2:$K$100,2,TRUE) -> Mcdonald Inc | Y12: =VLOOKUP(Q12,stores_imp!$A$2:$E$22,4,FALSE) -> Christopherland | Z12: =VLOOKUP(Q12,stores_imp!$A$2:$K$22,5,FALSE) -> Outlet | AA12: =_xlfn.IFS(sale[[#All],[Age]]<19,"Teens",sale[[#All],[Age]]<30,"Adults",sale[[#All],[Age]]<70,"Elders") -> Adults | AB12: =VLOOKUP(C12,customer_imp!$A$2:$H$505,8,FALSE) -> Silver
A13: Sale11 | B13: 45801 | C13: Cust1320 | D13: =VLOOKUP(C13,customer_imp!$A$2:$H$502,2,FALSE) -> Jessica Gonzalez | E13: =VLOOKUP(C13,customer_imp!$A$2:$H$502,3,FALSE) -> 34 | F13: =VLOOKUP(C13,customer_imp!$A$2:$H$502,4,FALSE) -> Female | G13: =VLOOKUP(C13,customer_imp!$A$2:$H$502,5,FALSE) -> South Darrenland | H13: =VLOOKUP(C13,customer_imp!$A$2:$H$502,6,FALSE) -> Iowa | I13: =VLOOKUP(C13,customer_imp!$A$2:$H$502,7,FALSE) -> USA | J13: Prod39 | K13: =VLOOKUP($J13,prod_imp!$A$2:$I$102,2,FALSE) -> Portable Power Bank | L13: =VLOOKUP(J13,prod_imp!$A$2:$I$102,3,FALSE) -> Electronics | M13: =VLOOKUP(J13,prod_imp!$A$2:$I$102,4,FALSE) -> Mobile | N13: =VLOOKUP(J13,prod_imp!$A$2:$I$102,5,FALSE) -> Cummings And Sons | O13: =VLOOKUP(J13,prod_imp!$A$2:$I$102,6,FALSE) -> 326 | P13: =VLOOKUP(J13,prod_imp!$A$2:$I$102,7,FALSE) -> 301 | Q13: Store1 | R13: Credit Card | S13: 952.5744 | T13: 4 | U13: 287 | V13: 0.07 | W13: =VLOOKUP(Q13,stores_imp!$A$2:$K$100,3,FALSE) -> NORTH | X13: =VLOOKUP(Q13,stores_imp!$A$2:$K$100,2,TRUE) -> Martinez, Adkins And Johnson | Y13: =VLOOKUP(Q13,stores_imp!$A$2:$E$22,4,FALSE) -> Danielmouth | Z13: =VLOOKUP(Q13,stores_imp!$A$2:$K$22,5,FALSE) -> Flagship | AA13: =_xlfn.IFS(sale[[#All],[Age]]<19,"Teens",sale[[#All],[Age]]<30,"Adults",sale[[#All],[Age]]<70,"Elders") -> Elders | AB13: =VLOOKUP(C13,customer_imp!$A$2:$H$505,8,FALSE) -> Bronze
... A2000: Sale1998 | B2000: 45607 | C2000: Cust1052 | D2000: =VLOOKUP(C2000,customer_imp!$A$2:$H$502,2,FALSE) -> Debra Liu | E2000: =VLOOKUP(C2000,customer_imp!$A$2:$H$502,3,FALSE) -> 55 | F2000: =VLOOKUP(C2000,customer_imp!$A$2:$H$502,4,FALSE) -> Male | G2000: =VLOOKUP(C2000,customer_imp!$A$2:$H$502,5,FALSE) -> South Timtown | H2000: =VLOOKUP(C2000,customer_imp!$A$2:$H$502,6,FALSE) -> Minnesota | I2000: =VLOOKUP(C2000,customer_imp!$A$2:$H$502,7,FALSE) -> USA | J2000: Prod61 | K2000: =VLOOKUP($J2000,prod_imp!$A$2:$I$102,2,FALSE) -> Tennis Ball 3-Pack | L2000: =VLOOKUP(J2000,prod_imp!$A$2:$I$102,3,FALSE) -> Sports | M2000: =VLOOKUP(J2000,prod_imp!$A$2:$I$102,4,FALSE) -> Equipment | N2000: =VLOOKUP(J2000,prod_imp!$A$2:$I$102,5,FALSE) -> Lopez Llc | O2000: =VLOOKUP(J2000,prod_imp!$A$2:$I$102,6,FALSE) -> 103 | P2000: =VLOOKUP(J2000,prod_imp!$A$2:$I$102,7,FALSE) -> 465 | Q2000: Store11 | R2000: Credit Card | S2000: 2694.3045 | T2000: 3 | U2000: 945 | V2000: 0.26 | W2000: =VLOOKUP(Q2000,stores_imp!$A$2:$K$100,3,FALSE) -> SOUTH | X2000: =VLOOKUP(Q2000,stores_imp!$A$2:$K$100,2,TRUE) -> Aguirre-Keller | Y2000: =VLOOKUP(Q2000,stores_imp!$A$2:$E$22,4,FALSE) -> Lake Michael | Z2000: =VLOOKUP(Q2000,stores_imp!$A$2:$K$22,5,FALSE) -> Online | AA2000: =_xlfn.IFS(sale[[#All],[Age]]<19,"Teens",sale[[#All],[Age]]<30,"Adults",sale[[#All],[Age]]<70,"Elders") -> Elders | AB2000: =VLOOKUP(C2000,customer_imp!$A$2:$H$505,8,FALSE) -> Bronze
A2001: Sale1999 | B2001: 45267 | C2001: Cust1023 | D2001: =VLOOKUP(C2001,customer_imp!$A$2:$H$502,2,FALSE) -> Jonathan Steele | E2001: =VLOOKUP(C2001,customer_imp!$A$2:$H$502,3,FALSE) -> 52 | F2001: =VLOOKUP(C2001,customer_imp!$A$2:$H$502,4,FALSE) -> Female | G2001: =VLOOKUP(C2001,customer_imp!$A$2:$H$502,5,FALSE) -> Molinabury | H2001: =VLOOKUP(C2001,customer_imp!$A$2:$H$502,6,FALSE) -> Oregon | I2001: =VLOOKUP(C2001,customer_imp!$A$2:$H$502,7,FALSE) -> USA | J2001: Prod76 | K2001: =VLOOKUP($J2001,prod_imp!$A$2:$I$102,2,FALSE) -> Wireless Mouse | L2001: =VLOOKUP(J2001,prod_imp!$A$2:$I$102,3,FALSE) -> Electronics | M2001: =VLOOKUP(J2001,prod_imp!$A$2:$I$102,4,FALSE) -> Computer | N2001: =VLOOKUP(J2001,prod_imp!$A$2:$I$102,5,FALSE) -> Larson Ltd | O2001: =VLOOKUP(J2001,prod_imp!$A$2:$I$102,6,FALSE) -> 393 | P2001: =VLOOKUP(J2001,prod_imp!$A$2:$I$102,7,FALSE) -> 320 | Q2001: Store19 | R2001: Paypal | S2001: 170.4405 | W2001: =VLOOKUP(Q2001,stores_imp!$A$2:$K$100,3,FALSE) -> EAST | X2001: =VLOOKUP(Q2001,stores_imp!$A$2:$K$100,2,TRUE) -> Mann-Austin | Y2001: =VLOOKUP(Q2001,stores_imp!$A$2:$E$22,4,FALSE) -> Vasquezborough | Z2001: =VLOOKUP(Q2001,stores_imp!$A$2:$K$22,5,FALSE) -> Online | AA2001: =_xlfn.IFS(sale[[#All],[Age]]<19,"Teens",sale[[#All],[Age]]<30,"Adults",sale[[#All],[Age]]<70,"Elders") -> Elders | AB2001: =VLOOKUP(C2001,customer_imp!$A$2:$H$505,8,FALSE) -> Silver

Sheet SAL
A1: Sales_ID | B1: Order_Date | C1: Customer_ID | D1: Product_ID | E1: Store_ID | F1: Quantity | G1: Unit_Price | H1: Discount | I1: Payment_Type | J1: Total_Amount
A2: SALE0 | B2: 45480 | C2: CUST1409 | D2: PROD97 | E2: STORE3 | F2: 1 | G2: 218.04 | H2: 0.09 | I2: Credit Card | J2: 198.4164
A3: SALE1 | B3: 45285 | C3: CUST1467 | D3: PROD74 | E3: STORE17 | F3: 3 | G3: 104.47 | H3: 0.27 | I3: PayPal | J3: 228.7893
A4: SALE2 | B4: 45446 | C4: CUST1056 | D4: PROD49 | E4: STORE8 | F4: 4 | G4: 914.05 | H4: 0.25 | I4: Credit Card | J4: 2742.15
A5: SALE3 | B5: 45259 | C5: CUST1346 | D5: PROD76 | E5: STORE8 | F5: 1 | G5: 921.51 | H5: 0.16 | I5: COD | J5: 774.0684
A6: SALE4 | B6: 45297 | C6: CUST1493 | D6: PROD59 | E6: STORE5 | F6: 3 | G6: 745.3 | H6: 0.18 | I6: Credit Card | J6: 1833.438
A7: SALE5 | B7: 45499 | C7: CUST1116 | D7: PROD15 | E7: STORE7 | F7: 3 | G7: 147.01 | H7: 0.19 | I7: COD | J7: 357.2343
A8: SALE6 | B8: 45850 | C8: CUST1016 | D8: PROD56 | E8: STORE4 | F8: 2 | G8: 785.31 | H8: 0.15 | I8: PayPal | J8: 1335.027
A9: SALE7 | B9: 45248 | C9: CUST1152 | D9: PROD70 | E9: STORE8 | F9: 4 | G9: 342.39 | H9: 0.23 | I9: PayPal | J9: 1054.5612
A10: SALE8 | B10: 45781 | C10: CUST1187 | D10: PROD99 | E10: STORE5 | G10: 448.25 | H10: 0.07 | I10: PayPal | J10: 1250.6175
A11: SALE9 | B11: 45869 | C11: CUST1464 | D11: PROD33 | E11: STORE0 | F11: 2 | G11: 873.17 | H11: 0.23 | I11: PayPal | J11: 1344.6818
A12: SALE10 | B12: 45335 | C12: CUST1065 | D12: PROD24 | E12: STORE14 | F12: 1 | G12: 278.63 | H12: 0.07 | I12: Credit Card | J12: 259.1259
A13: SALE11 | B13: 45801 | C13: CUST1320 | D13: PROD39 | E13: STORE1 | F13: 4 | G13: 286.92 | H13: 0.17 | I13: Credit Card | J13: 952.5744
A14: SALE12 | B14: 45528 | C14: CUST1237 | D14: PROD88 | E14: STORE4 | F14: 4 | G14: 644.58 | H14: 0.01 | I14: Credit Card | J14: 2552.5368
A15: SALE13 | B15: 45875 | C15: CUST1443 | D15: PROD34 | E15: STORE16 | F15: 2 | G15: 316.9 | H15: 0.3 | I15: PayPal | J15: 443.66
A16: SALE14 | B16: 45829 | C16: CUST1348 | D16: PROD24 | E16: STORE15 | F16: 4 | G16: 403.47 | H16: 0.29 | I16: PayPal | J16: 1145.8548
A17: SALE15 | B17: 45636 | C17: CUST1435 | D17: PROD36 | E17: STORE9 | G17: 871.34 | H17: 0.04 | I17: COD | J17: 2509.4592
A18: SALE16 | B18: 45913 | C18: CUST1276 | D18: PROD65 | E18: STORE19 | F18: 2 | G18: 451.98 | H18: 0.25 | I18: Credit Card | J18: 677.97
A19: SALE17 | B19: 45637 | C19: CUST1079 | D19: PROD27 | E19: STORE4 | F19: 2 | G19: 502.69 | H19: 0.23 | I19: Credit Card | J19: 774.1426
A20: SALE18 | B20: 45517 | C20: CUST1094 | D20: PROD39 | E20: STORE4 | F20: 2 | G20: 559.23 | H20: 0.25 | I20: COD | J20: 838.845
A21: SALE19 | B21: 45369 | C21: CUST1239 | D21: PROD60 | E21: STORE13 | F21: 4 | H21: 0.04 | I21: COD | J21: 1782.4512
A22: SALE20 | B22: 45843 | C22: CUST1144 | D22: PROD72 | E22: STORE17 | F22: 3 | G22: 986.04 | H22: 0.27 | I22: COD | J22: 2159.4276
A23: SALE21 | B23: 45447 | C23: CUST1396 | D23: PROD43 | E23: STORE18 | F23: 1 | G23: 589.56 | H23: 0.22 | I23: Credit Card | J23: 459.8568
A24: SALE22 | B24: 45394 | C24: CUST1476 | D24: PROD69 | E24: STORE10 | F24: 3 | G24: 979.42 | H24: 0.03 | I24: PayPal | J24: 2850.1122
A25: SALE23 | B25: 45466 | C25: CUST1368 | D25: PROD12 | E25: STORE8 | F25: 1 | G25: 719.28 | H25: 0.08 | I25: Credit Card | J25: 661.7376
A26: SALE24 | B26: 45908 | C26: CUST1186 | D26: PROD67 | E26: STORE6 | F26: 3 | G26: 77.6 | H26: 0.07 | I26: Credit Card | J26: 216.504
A27: SALE25 | B27: 45552 | C27: CUST1381 | D27: PROD5 | E27: STORE3 | F27: 4 | G27: 852.71 | H27: 0.14 | I27: PayPal | J27: 2933.3224
A28: SALE26 | B28: 45294 | C28: CUST1213 | D28: PROD98 | E28: STORE8 | F28: 4 | G28: 156.16 | I28: Credit Card | J28: 599.6544
A29: SALE27 | B29: 45710 | C29: CUST1200 | D29: PROD77 | E29: STORE8 | F29: 3 | G29: 815.49 | H29: 0.17 | I29: Credit Card | J29: 2030.5701
A30: SALE28 | B30: 45923 | C30: CUST1148 | D30: PROD13 | E30: STORE2 | F30: 2 | G30: 74.21 | H30: 0.11 | I30: PayPal | J30: 132.0938
A31: SALE29 | B31: 45302 | C31: CUST1348 | D31: PROD99 | E31: STORE3 | G31: 451.67 | H31: 0.15 | I31: Credit Card | J31: 1535.678
A32: SALE30 | B32: 45217 | C32: CUST1028 | D32: PROD5 | E32: STORE19 | F32: 1 | G32: 429.38 | H32: 0.13 | I32: PayPal | J32: 373.5606
A33: SALE31 | B33: 45593 | C33: CUST1412 | D33: PROD53 | E33: STORE12 | F33: 2 | G33: 148.96 | H33: 0.03 | I33: COD | J33: 288.9824
A34: SALE32 | B34: 45597 | C34: CUST1398 | D34: PROD75 | E34: STORE8 | F34: 4 | G34: 313.83 | H34: 0.08 | I34: Credit Card | J34: 1154.8944
A35: SALE33 | B35: 45620 | C35: CUST1453 | D35: PROD12 | E35: STORE6 | F35: 2 | G35: 717.31 | H35: 0.15 | I35: Credit Card | J35: 1219.427
A36: SALE34 | B36: 45215 | C36: CUST1344 | D36: PROD79 | E36: STORE1 | G36: 873.22 | H36: 0.18 | I36: Credit Card | J36: 2148.1212
A37: SALE35 | B37: 45878 | C37: CUST1218 | D37: PROD16 | E37: STORE3 | F37: 4 | G37: 109.36 | H37: 0.19 | I37: COD | J37: 354.3264
A38: SALE36 | B38: 45635 | C38: CUST1086 | D38: PROD5 | E38: STORE7 | F38: 3 | G38: 559.52 | H38: 0.16 | I38: PayPal | J38: 1409.9904
A39: SALE37 | B39: 45329 | C39: CUST1492 | D39: PROD10 | E39: STORE17 | F39: 3 | G39: 121.76 | H39: 0.27 | I39: PayPal | J39: 266.6544
A40: SALE38 | B40: 45378 | C40: CUST1189 | D40: PROD33 | E40: STORE13 | F40: 4 | G40: 735.32 | H40: 0.06 | I40: COD | J40: 2764.8032
A41: SALE39 | B41: 45264 | C41: CUST1431 | D41: PROD94 | E41: STORE3 | F41: 2 | G41: 600.73 | H41: 0.08 | I41: Credit Card | J41: 1105.3432
A42: SALE40 | B42: 45486 | C42: CUST1072 | D42: PROD26 | E42: STORE19 | F42: 2 | G42: 873.86 | H42: 0.07 | I42: COD | J42: 1625.3796
A43: SALE41 | B43: 45241 | C43: CUST1302 | D43: PROD23 | E43: STORE8 | F43: 3 | G43: 342.47 | H43: 0.08 | I43: PayPal | J43: 945.2172
A44: SALE42 | B44: 45649 | C44: CUST1335 | D44: PROD29 | E44: STORE9 | F44: 2 | G44: 915.15 | H44: 0.16 | I44: PayPal | J44: 1537.452
A45: SALE43 | B45: 45677 | C45: CUST1084 | D45: PROD33 | E45: STORE17 | G45: 863.11 | H45: 0.28 | I45: PayPal | J45: 1864.3176
A46: SALE44 | B46: 45538 | C46: CUST1203 | D46: PROD43 | E46: STORE12 | F46: 2 | G46: 209.32 | H46: 0.23 | I46: COD | J46: 322.3528
A47: SALE45 | B47: 45606 | C47: CUST1470 | D47: PROD59 | E47: STORE8 | F47: 4 | G47: 288.6 | H47: 0.09 | I47: PayPal | J47: 1050.504
A48: SALE46 | B48: 45570 | C48: CUST1070 | D48: PROD78 | E48: STORE16 | F48: 1 | G48: 418.69 | H48: 0.06 | I48: PayPal | J48: 393.5686
A49: SALE47 | B49: 45466 | C49: CUST1008 | D49: PROD30 | E49: STORE11 | F49: 1 | G49: 135.78 | H49: 0.14 | I49: PayPal | J49: 116.7708
A50: SALE48 | B50: 45218 | C50: CUST1203 | D50: PROD44 | E50: STORE17 | F50: 1 | G50: 517.13 | H50: 0.28 | I50: Credit Card | J50: 372.3336
A51: SALE49 | B51: 45607 | C51: CUST1420 | D51: PROD21 | E51: STORE16 | F51: 2 | G51: 384.66 | H51: 0.08 | I51: COD | J51: 707.7744
A52: SALE50 | B52: 45291 | C52: CUST1070 | D52: PROD52 | E52: STORE9 | F52: 3 | G52: 83.7 | H52: 0.24 | I52: PayPal | J52: 190.836
A53: SALE51 | B53: 45689 | C53: CUST1142 | D53: PROD69 | E53: STORE7 | F53: 3 | G53: 76.57 | H53: 0.26 | I53: Credit Card | J53: 169.9854
A54: SALE52 | B54: 45894 | C54: CUST1148 | D54: PROD89 | E54: STORE6 | F54: 3 | I54: Credit Card | J54: 486.0633
A55: SALE53 | B55: 45677 | C55: CUST1324 | D55: PROD20 | E55: STORE8 | F55: 1 | G55: 900.35 | H55: 0.13 | I55: COD | J55: 783.3045
A56: SALE54 | B56: 45706 | C56: CUST1095 | D56: PROD40 | E56: STORE10 | F56: 4 | G56: 428.09 | H56: 0.07 | I56: Credit Card | J56: 1592.4948
A57: SALE55 | B57: 45589 | C57: CUST1416 | D57: PROD49 | E57: STORE11 | F57: 2 | G57: 559.71 | H57: 0.3 | I57: COD | J57: 783.594
A58: SALE56 | B58: 45282 | C58: CUST1080 | D58: PROD34 | E58: STORE6 | F58: 2 | G58: 833.7 | H58: 0.06 | I58: PayPal | J58: 1567.356
A59: SALE57 | B59: 45462 | C59: CUST1467 | D59: PROD47 | E59: STORE14 | F59: 2 | G59: 680.16 | H59: 0.28 | I59: Credit Card | J59: 979.4304
A60: SALE58 | B60: 45633 | C60: CUST1404 | D60: PROD15 | E60: STORE7 | F60: 4 | G60: 733.42 | I60: PayPal | J60: 2552.3016
A61: SALE59 | B61: 45257 | C61: CUST1367 | D61: PROD89 | E61: STORE11 | F61: 1 | G61: 996.33 | H61: 0.23 | I61: PayPal | J61: 767.1741
A62: SALE60 | B62: 45854 | C62: CUST1408 | D62: PROD31 | E62: STORE10 | F62: 1 | G62: 198.83 | H62: 0.09 | I62: COD | J62: 180.9353
A63: SALE61 | B63: 45716 | C63: CUST1239 | D63: PROD19 | E63: STORE7 | F63: 1 | G63: 374.92 | H63: 0.18 | I63: PayPal | J63: 307.4344
A64: SALE62 | B64: 45515 | C64: CUST1464 | D64: PROD93 | E64: STORE16 | F64: 1 | G64: 468.94 | H64: 0.12 | I64: Credit Card | J64: 412.6672
A65: SALE63 | B65: 45927 | C65: CUST1126 | D65: PROD89 | E65: STORE12 | F65: 2 | G65: 121.37 | H65: 0.05 | I65: Credit Card | J65: 230.603
A66: SALE64 | B66: 45914 | C66: CUST1255 | D66: PROD53 | E66: STORE10 | F66: 3 | G66: 480.06 | H66: 0.01 | I66: Credit Card
A67: SALE65 | B67: 45290 | C67: CUST1162 | D67: PROD99 | E67: STORE17 | F67: 2 | G67: 856.57 | H67: 0.24 | I67: Credit Card | J67: 1301.9864
A68: SALE66 | B68: 45213 | C68: CUST1269 | D68: PROD77 | E68: STORE2 | F68: 4 | G68: 814.25 | H68: 0.18 | I68: Credit Card | J68: 2670.74
A69: SALE67 | B69: 45255 | C69: CUST1483 | D69: PROD12 | E69: STORE2 | F69: 1 | G69: 989.17 | H69: 0.2 | I69: PayPal | J69: 791.336
A70: SALE68 | B70: 45270 | C70: CUST1372 | D70: PROD72 | E70: STORE10 | F70: 4 | G70: 62.48 | H70: 0.18 | I70: Credit Card | J70: 204.9344
A71: SALE69 | B71: 45897 | C71: CUST1423 | D71: PROD13 | E71: STORE16 | F71: 4 | G71: 561.24 | H71: 0.24 | I71: Credit Card | J71: 1706.1696
A72: SALE70 | B72: 45849 | C72: CUST1058 | D72: PROD60 | E72: STORE5 | F72: 3 | G72: 92.24 | H72: 0.28 | I72: COD
A73: SALE71 | B73: 45889 | C73: CUST1168 | D73: PROD72 | E73: STORE1 | F73: 2 | G73: 668.3 | H73: 0.07 | I73: Credit Card | J73: 1243.038
A74: SALE72 | B74: 45533 | C74: CUST1409 | D74: PROD38 | E74: STORE5 | F74: 1 | G74: 553.82 | H74: 0.09 | I74: Credit Card | J74: 503.9762
A75: SALE73 | B75: 45626 | C75: CUST1037 | D75: PROD45 | E75: STORE11 | F75: 2 | G75: 556.43 | H75: 0.13 | I75: Credit Card | J75: 968.1882
A76: SALE74 | B76: 45942 | C76: CUST1273 | D76: PROD20 | E76: STORE8 | F76: 1 | G76: 184.98 | H76: 0.1 | I76: COD | J76: 166.482
A77: SALE75 | B77: 45500 | C77: CUST1035 | D77: PROD97 | E77: STORE12 | F77: 4 | G77: 700.18 | H77: 0.23 | I77: Credit Card | J77: 2156.5544
A78: SALE76 | B78: 45285 | C78: CUST1019 | D78: PROD76 | E78: STORE10 | F78: 2 | G78: 686.31 | H78: 0.25 | I78: Credit Card | J78: 1029.465
A79: SALE77 | B79: 45800 | C79: CUST1007 | D79: PROD67 | E79: STORE15 | F79: 1 | G79: 687.82 | H79: 0.27 | I79: COD | J79: 502.1086
A80: SALE78 | B80: 45609 | C80: CUST1221 | D80: PROD83 | E80: STORE8 | F80: 2 | G80: 900.55 | H80: 0.16 | I80: Credit Card | J80: 1512.924
A81: SALE79 | B81: 45268 | C81: CUST1115 | D81: PROD21 | E81: STORE2 | F81: 1 | G81: 341.17 | H81: 0.15 | I81: Credit Card | J81: 289.9945
A82: SALE80 | B82: 45885 | C82: CUST1176 | D82: PROD52 | E82: STORE8 | F82: 1 | G82: 442.27 | H82: 0.06 | I82: COD | J82: 415.7338
A83: SALE81 | B83: 45616 | C83: CUST1253 | D83: PROD71 | E83: STORE9 | F83: 1 | G83: 363.73 | H83: 0.25 | I83: PayPal | J83: 272.7975
A84: SALE82 | B84: 45518 | C84: CUST1378 | D84: PROD91 | E84: STORE17 | F84: 2 | G84: 601.33 | H84: 0.16 | I84: PayPal | J84: 1010.2344
A85: SALE83 | B85: 45427 | C85: CUST1403 | D85: PROD17 | E85: STORE18 | F85: 4 | G85: 34.39 | H85: 0.03 | I85: PayPal | J85: 133.4332
A86: SALE84 | B86: 45268 | C86: CUST1423 | D86: PROD46 | E86: STORE17 | F86: 1 | G86: 773.57 | H86: 0.05 | I86: COD
A87: SALE85 | B87: 45282 | C87: CUST1054 | D87: PROD88 | E87: STORE7 | F87: 4 | G87: 127.1 | H87: 0.24 | I87: COD | J87: 386.384
A88: SALE86 | B88: 45545 | C88: CUST1303 | D88: PROD20 | E88: STORE3 | F88: 3 | G88: 899.58 | H88: 0.28 | I88: PayPal | J88: 1943.0928
A89: SALE87 | B89: 45755 | C89: CUST1327 | D89: PROD1 | E89: STORE10 | F89: 3 | G89: 964.39 | H89: 0.04 | I89: Credit Card | J89: 2777.4432
A90: SALE88 | B90: 45588 | C90: CUST1183 | D90: PROD38 | E90: STORE0 | F90: 2 | G90: 217.83 | H90: 0.14 | I90: PayPal | J90: 374.6676
A91: SALE89 | B91: 45848 | C91: CUST1143 | D91: PROD17 | E91: STORE1 | F91: 4 | G91: 187.71 | H91: 0.06 | I91: COD | J91: 705.7896
A92: SALE90 | B92: 45577 | C92: CUST1010 | D92: PROD33 | E92: STORE18 | F92: 2 | G92: 350.12 | H92: 0.12 | I92: COD | J92: 616.2112
A93: SALE91 | B93: 45312 | C93: CUST1406 | D93: PROD16 | E93: STORE1 | F93: 4 | G93: 102.19 | H93: 0.17 | I93: PayPal | J93: 339.2708
A94: SALE92 | B94: 45350 | C94: CUST1007 | D94: PROD86 | E94: STORE4 | F94: 1 | G94: 696.53 | H94: 0.17 | I94: Credit Card | J94: 578.1199
A95: SALE93 | B95: 45657 | C95: CUST1065 | D95: PROD19 | E95: STORE4 | F95: 2 | G95: 327.52 | H95: 0.15 | I95: PayPal | J95: 556.784
A96: SALE94 | B96: 45530 | C96: CUST1298 | D96: PROD97 | E96: STORE19 | F96: 2 | G96: 569.36 | H96: 0.01 | I96: PayPal
A97: SALE95 | B97: 45556 | C97: CUST1321 | D97: PROD99 | E97: STORE6 | F97: 2 | G97: 68.29 | H97: 0.14 | I97: COD | J97: 117.4588
A98: SALE96 | B98: 45523 | C98: CUST1244 | D98: PROD50 | E98: STORE10 | F98: 1 | G98: 842.9 | H98: 0.06 | I98: COD | J98: 792.326
A99: SALE97 | B99: 45587 | C99: CUST1287 | D99: PROD3 | E99: STORE3 | F99: 3 | G99: 751.94 | H99: 0.26 | I99: PayPal | J99: 1669.3068
A100: SALE98 | B100: 45580 | C100: CUST1131 | D100: PROD56 | E100: STORE7 | F100: 4 | G100: 476.28 | H100: 0.17 | I100: Credit Card | J100: 1581.2496
...

Sheet DASHBOARD

Sheet Sheet1
